karaone/.env
karaone/__init__.py
karaone/__main__.py
karaone/cli.py
karaone/split.py
karaone-0.1.0.dist-info/METADATA
karaone-0.1.0.dist-info/WHEEL
karaone-0.1.0.dist-info/entry_points.txt
karaone-0.1.0.dist-info/top_level.txt
karaone-0.1.0.dist-info/RECORD
