Metadata-Version: 2.1
Name: karaone
Version: 0.1.0
Summary: A simple utils tools for kara ona database eeg
Home-page: https://github.com/unlikeghost/karaone
Author: unlikeghost
Author-email: unlikeghost@protonmail.com
License: UNKNOWN
Platform: UNKNOWN
Classifier: Programming Language :: Python :: 3
Requires-Python: >=3.6
Requires-Dist: mne
Requires-Dist: typer
Requires-Dist: requests
Requires-Dist: matplotlib
Requires-Dist: numpy
Requires-Dist: scipy
Requires-Dist: python-dotenv
